ab_core/token_issuer/schema/__init__.py
ab_core/token_issuer/schema/token_issuer_type.py
ab_core/token_issuer/token_issuers/__init__.py
ab_core/token_issuer/token_issuers/base.py
ab_core/token_issuer/token_issuers/oauth2.py
ab_core/token_issuer/token_issuers/pkce.py
ab_core/token_issuer/token_issuers/template.py
ab_token_issuer-0.2.3.dist-info/METADATA
ab_token_issuer-0.2.3.dist-info/WHEEL
ab_token_issuer-0.2.3.dist-info/licenses/LICENSE
ab_token_issuer-0.2.3.dist-info/RECORD
