Metadata-Version: 2.4
Name: ab-token-issuer
Version: 0.2.3
Author-email: Matthew Coulter <53892067+mattcoulter7@users.noreply.github.com>
License-File: LICENSE
Requires-Python: <4,>=3.12
Requires-Dist: ab-auth-client<0.2.0,>=0.1.6
Requires-Dist: ab-auth-flow<0.3.0,>=0.2.5
Requires-Dist: ab-cache<0.2.0,>=0.1.4
Requires-Dist: ab-dependency<0.3.0,>=0.2.0
Requires-Dist: ab-pkce<0.2.0,>=0.1.3
Requires-Dist: uuid7<0.2,>=0.1.0
Requires-Dist: yarl<2,>=1.20.1
